USB_Quartermaster_VirtualHere/__init__.py
USB_Quartermaster_VirtualHere/driver.py
USB_Quartermaster_VirtualHere/tasks.py
usb_quartermaster_virtualhere-0.1.0.dist-info/WHEEL
usb_quartermaster_virtualhere-0.1.0.dist-info/METADATA
usb_quartermaster_virtualhere-0.1.0.dist-info/RECORD
